aetcd3/__init__.py
aetcd3/client.py
aetcd3/events.py
aetcd3/exceptions.py
aetcd3/leases.py
aetcd3/locks.py
aetcd3/members.py
aetcd3/transactions.py
aetcd3/utils.py
aetcd3/watch.py
aetcd3/rpc/__init__.py
aetcd3/rpc/auth_grpc.py
aetcd3/rpc/auth_pb2.py
aetcd3/rpc/kv_grpc.py
aetcd3/rpc/kv_pb2.py
aetcd3/rpc/rpc_grpc.py
aetcd3/rpc/rpc_pb2.py
aetcd3-0.1.0a7.post1.dist-info/LICENSE
aetcd3-0.1.0a7.post1.dist-info/METADATA
aetcd3-0.1.0a7.post1.dist-info/WHEEL
aetcd3-0.1.0a7.post1.dist-info/top_level.txt
aetcd3-0.1.0a7.post1.dist-info/RECORD
