Metadata-Version: 2.1
Name: aetcd3
Version: 0.1.0a7.post1
Summary: NOTICE: Please use aetcd package instead
Home-page: https://github.com/martyanov/aetcd3
Author: Andrey Martyanov
Author-email: andrey@martyanov.com
License: Apache Software License 2.0
Project-URL: Documentation, https://aetcd3.readthedocs.io
Project-URL: Code, https://github.com/martyanov/aetcd3
Project-URL: Issues, https://github.com/martyanov/aetcd3/issues
Keywords: etcd3
Platform: UNKNOWN
Classifier: Development Status :: 3 - Alpha
Classifier: Intended Audience :: Developers
Classifier: License :: OSI Approved :: Apache Software License
Classifier: Programming Language :: Python :: 3
Classifier: Programming Language :: Python :: 3.8
Classifier: Programming Language :: Python :: 3.9
Requires-Python: >=3.8,<4.0
Requires-Dist: aiofiles (<0.7,>=0.5)
Requires-Dist: grpclib (<0.5,>=0.4.1)
Requires-Dist: protobuf (<4,>=3)
Requires-Dist: tenacity (<7,>=6)
Provides-Extra: dev
Requires-Dist: flake8-commas (==2.0.0) ; extra == 'dev'
Requires-Dist: flake8-docstrings (==1.6.0) ; extra == 'dev'
Requires-Dist: flake8-isort (==4.0.0) ; extra == 'dev'
Requires-Dist: flake8-quotes (==3.2.0) ; extra == 'dev'
Requires-Dist: flake8 (==3.9.1) ; extra == 'dev'
Requires-Dist: grpcio-tools (==1.37.0) ; extra == 'dev'
Requires-Dist: pep8-naming (==0.11.1) ; extra == 'dev'
Requires-Dist: twine (==3.4.1) ; extra == 'dev'
Provides-Extra: doc
Requires-Dist: sphinx (==3.5.4) ; extra == 'doc'
Requires-Dist: sphinx-rtd-theme (==0.5.2) ; extra == 'doc'
Provides-Extra: test
Requires-Dist: pifpaf (==3.1.5) ; extra == 'test'
Requires-Dist: pytest-asyncio (==0.15.1) ; extra == 'test'
Requires-Dist: pytest-cov (==2.11.1) ; extra == 'test'
Requires-Dist: pytest (==6.2.3) ; extra == 'test'
